Controller.v
module Controller(
    clock,
    Reset,
    IncA,
    IncB,
    WEA,
    WEB,
    counter
);

input clock, Reset;

output IncA, IncB, WEA, WEB;
output [4:0] counter;

wire clock, Reset;
reg IncA, IncB, WEA, WEB;
reg [4:0] counter = 5'b00000;

always @(posedge clock) 
begin
    if(Reset == 1'b1 || counter == 5'b10010)
        counter = 5'b0;
    else
        counter = counter + 1;
    
    if(counter >= 5'd1 && counter <= 5'd8)
        WEA = 1'b1;
    else
        WEA = 1'b0;

    if(counter != 5'b10001 && counter != 5'b10010 && counter != 5'b10011)
		IncA = 1;
	else
        IncA = 0;

	if(counter == 5'b01011 || counter == 5'b01101 || counter == 5'b01111 || counter == 5'b10001)
		WEB = 1;
	else
        WEB = 0;

	if(counter == 5'b01100 || counter == 5'b01110 || counter == 5'b10000 || counter == 5'b10010)
		IncB = 1;
	else
        IncB = 0;
end

endmodule

Comparator.v
module Comparator(
    DOut1,
    DOut2,
    Sign
);

input [7:0]DOut1,DOut2;
output Sign;

wire [7:0] DOut1;
wire [7:0] DOut2;
reg Sign;

always @(*)
if(DOut1 > DOut2)
    Sign <= 0;
else
    Sign <= 1;

endmodule

Subber.v
module Subber(
    DOut1, 
    DOut2,
    SUBOut
);

input [7:0] DOut1;
input [7:0] DOut2;
output [7:0] SUBOut;

wire [7:0] DOut1;
wire [7:0] DOut2;
reg [7:0] SUBOut;

always @ (*)
SUBOut <= DOut1 - DOut2;

endmodule

Adder.v
module Adder(
    DOut1, 
    DOut2,
    ADDOut
);

input [7:0] DOut1;
input [7:0] DOut2;
output [7:0] ADDOut;

wire [7:0] DOut1;
wire [7:0] DOut2;
reg [7:0] ADDOut;

always @(*)
    ADDOut <= DOut1 + DOut2;

endmodule

D_Flip_Flop.v
module D_Flip_Flop(
    DOut1,
    clock,
    DOut2
);

input [7:0] DOut1;
input clock;
output [7:0] DOut2;

wire [7:0] DOut1;
wire clock;
reg [7:0] DOut2;

always @(posedge clock)
    DOut2 <= DOut1;

endmodule

MC_B.v
module MC_B (
    IncB,
    Reset,
    clock,
    AddrB,
    WEB,
    DataInB
);

input IncB, WEB, Reset, clock;
input [7:0] DataInB;
output [1:0] AddrB;

wire IncB, WEB, Reset, clock;
reg [1:0] AddrB;
reg [7:0] MemB[0:3];

always @(posedge clock)
    begin
        if(!Reset)
            begin
                if((IncB == 1'b0 && WEB == 1'b1) || (IncB == 1'b1 && WEB == 1'b0))
                    begin
                        if(WEB)
                            MemB[AddrB] <= DataInB;
                        if(IncB == 1'b0 && WEB == 1'b1)
                            AddrB = AddrB + 1;
                    end
                else
                    AddrB <= 2'b00;
            end
        else
            AddrB <= 2'b00;
    end

endmodule

MC_A.v
module MC_A (
    IncA,
    Reset,
    clock,
    AddrA,
    WEA,
    DataInA,
    DOut1
);

input IncA, WEA, Reset, clock;
input [7:0] DataInA;
output [7:0] DOut1;
output [2:0] AddrA;

wire IncA, WEA, Reset, clock;
reg [2:0] AddrA;
reg [7:0] DOut1;
reg [7:0] MemA[0:7];

always @(posedge clock)
    begin
        if(!Reset)
            begin
                if(IncA && WEA && !(DataInA === 8'bz))
                    begin
                        MemA[AddrA] = DataInA;
                        AddrA = AddrA + 1;
                    end
                else if(IncA && !WEA)
                    begin
                        DOut1 = MemA[AddrA];
                        AddrA = AddrA + 1;
                    end
                else if(!IncA && WEA && !(DataInA === 8'bz))
                    MemA[AddrA] = DataInA;
                else if(!IncA && !WEA)
                    DOut1 = MemA[AddrA];
            end
        else
            begin
                AddrA = 3'b000;
                DOut1 = 8'bz;
    end
end

endmodule

Memo_Trans_ts.v
`timescale 10ps/1ps
`include "MC_A.v"
`include "MC_B.v"
`include "D_Flip_Flop.v"
`include "Adder.v"
`include "Subber.v"
`include "Comparator.v"
`include "Controller.v"

module test;
reg Reset,clock,sign;
reg[7:0] DataInA;
wire WEA,WEB,IncA,IncB;
wire [2:0]AddrA;
wire [7:0]DOut1,DOut2,DataInB, ADDOut, SUBOut;
wire [1:0]AddrB;
wire [4:0]counter;

integer k = 0;

MC_A ma(
    .IncA(IncA),
    .Reset(Reset),
    .clock(clock),
    .AddrA(AddrA),
    .WEA(WEA),
    .DataInA(DataInA),
    .DOut1(DOut1)
);

MC_B mb(
    .IncB(IncB),
    .Reset(Reset),
    .clock(clock),
    .AddrB(AddrB),
    .WEB(WEB),
    .DataInB(DataInB)
);

D_Flip_Flop dff(
    .DOut1(DOut1),
    .clock(clock),
    .DOut2(DOut2)
);

Adder ad(
    .DOut1(DOut1),
    .DOut2(DOut2),
    .ADDOut(ADDOut)
);

Subber sb(
    .DOut1(DOut1),
    .DOut2(DOut2),
    .SUBOut(SUBOut)
);

Comparator cp(
    .DOut1(DOut1),
    .DOut2(DOut2),
    .Sign(Sign)
);

Controller ct(
    .clock(clock),
    .Reset(Reset),
    .IncA(IncA),
    .IncB(IncB),
    .WEA(WEA),
    .WEB(WEB),
    .counter(counter)
);

initial
begin
	clock = 1'b0;
	Reset = 1'b1;
	DataInA = 8'b0;
    for(k = 0; k < 20; k = k + 1)
    begin
          #10 clock = ~clock;
    end
end

initial
begin
    $dumpfile("memo_trans.vcd");
    $dumpvars(0, test);

	#10
	DataInA = 8'b0;
	repeat(8) begin
	#20 DataInA = DataInA + 1;
	end
	DataInA = 8'bz;
end

initial
begin
    #8 Reset = ~Reset;
    #360 Reset = 1'b1;
end
endmodule

memo_trans.vcd
$date
	Mon Mar 18 23:49:51 2019
$end
$version
	Icarus Verilog
$end
$timescale
	1ps
$end
$scope module test $end
$var wire 8 ! DataInB [7:0] $end
$var wire 5 " counter [4:0] $end
$var wire 1 # WEB $end
$var wire 1 $ WEA $end
$var wire 1 % Sign $end
$var wire 8 & SUBOut [7:0] $end
$var wire 1 ' IncB $end
$var wire 1 ( IncA $end
$var wire 8 ) DOut2 [7:0] $end
$var wire 8 * DOut1 [7:0] $end
$var wire 2 + AddrB [1:0] $end
$var wire 3 , AddrA [2:0] $end
$var wire 8 - ADDOut [7:0] $end
$var reg 8 . DataInA [7:0] $end
$var reg 1 / Reset $end
$var reg 1 0 clock $end
$var integer 32 1 k [31:0] $end
$scope module ad $end
$var wire 8 2 DOut2 [7:0] $end
$var wire 8 3 DOut1 [7:0] $end
$var reg 8 4 ADDOut [7:0] $end
$upscope $end
$scope module cp $end
$var wire 8 5 DOut2 [7:0] $end
$var wire 8 6 DOut1 [7:0] $end
$var reg 1 % Sign $end
$upscope $end
$scope module ct $end
$var wire 1 / Reset $end
$var wire 1 0 clock $end
$var reg 1 ( IncA $end
$var reg 1 ' IncB $end
$var reg 1 $ WEA $end
$var reg 1 # WEB $end
$var reg 5 7 counter [4:0] $end
$upscope $end
$scope module dff $end
$var wire 1 0 clock $end
$var wire 8 8 DOut1 [7:0] $end
$var reg 8 9 DOut2 [7:0] $end
$upscope $end
$scope module ma $end
$var wire 8 : DataInA [7:0] $end
$var wire 1 ( IncA $end
$var wire 1 / Reset $end
$var wire 1 $ WEA $end
$var wire 1 0 clock $end
$var reg 3 ; AddrA [2:0] $end
$var reg 8 < DOut1 [7:0] $end
$upscope $end
$scope module mb $end
$var wire 8 = DataInB [7:0] $end
$var wire 1 ' IncB $end
$var wire 1 / Reset $end
$var wire 1 # WEB $end
$var wire 1 0 clock $end
$var reg 2 > AddrB [1:0] $end
$upscope $end
$scope module sb $end
$var wire 8 ? DOut1 [7:0] $end
$var wire 8 @ DOut2 [7:0] $end
$var reg 8 A SUBOut [7:0] $end
$upscope $end
$upscope $end
$enddefinitions $end
#0
$dumpvars
bx A
bx @
bx ?
bx >
bz =
bx <
bx ;
b0 :
bx 9
bx 8
b0 7
bx 6
bx 5
bx 4
bx 3
bx 2
b0 1
00
1/
b0 .
bx -
bx ,
bx +
bx *
bx )
x(
x'
bx &
x%
x$
x#
b0 "
bz !
$end
#80
0/
#100
b0 +
b0 >
0'
0#
1(
1$
b1 "
b1 7
b1 1
10
#200
b10 1
00
#300
b10 "
b10 7
b11 1
10
b1 .
b1 :
#400
b100 1
00
#500
b11 "
b11 7
b101 1
10
b10 .
b10 :
#600
b110 1
00
#700
b100 "
b100 7
b111 1
10
b11 .
b11 :
#800
b1000 1
00
#900
b101 "
b101 7
b1001 1
10
b100 .
b100 :
#1000
b1010 1
00
#1100
b110 "
b110 7
b1011 1
10
b101 .
b101 :
#1200
b1100 1
00
#1300
b111 "
b111 7
b1101 1
10
b110 .
b110 :
#1400
b1110 1
00
#1500
b1000 "
b1000 7
b1111 1
10
b111 .
b111 :
#1600
b10000 1
00
#1700
0$
b1001 "
b1001 7
b10001 1
10
bz .
bz :
#1800
b10010 1
00
#1900
b1010 "
b1010 7
b10011 1
10
#2000
b10100 1
00
#3680
1/
