Subber.v
module Subber(
    DOut1, 
    DOut2,
    SUBOut
);

input [7:0] DOut1;
input [7:0] DOut2;
output [7:0] SUBOut;

wire [7:0] DOut1;
wire [7:0] DOut2;
reg [7:0] SUBOut;

always @ (*)
SUBOut <= DOut1 - DOut2;

endmodule

Subber_tb.v
`timescale 10ps/1ps
`include "Subber.v"

module Subber_tb;

reg [7:0] DOut1;
reg [7:0] DOut2;
wire [7:0] SUBOut;
integer k = 0;

Subber dut(
.DOut1(DOut1),
.DOut2(DOut2),
.SUBOut(SUBOut)
);

initial begin
    $dumpfile("subber.vcd");
    $dumpvars(0,Subber_tb);
    DOut1 = 8'h1;
    DOut2 = 8'hF;
    for(k=0;k<10;k=k+1)
        begin
        #5 DOut1 = DOut1 + 1;
        #5 DOut2 = DOut2 - 1;
        end
end

endmodule

subber.vcd
$date
	Tue Mar 19 15:41:57 2019
$end
$version
	Icarus Verilog
$end
$timescale
	1ps
$end
$scope module Subber_tb $end
$var wire 8 ! SUBOut [7:0] $end
$var reg 8 " DOut1 [7:0] $end
$var reg 8 # DOut2 [7:0] $end
$var integer 32 $ k [31:0] $end
$scope module dut $end
$var wire 8 % DOut1 [7:0] $end
$var wire 8 & DOut2 [7:0] $end
$var reg 8 ' SUBOut [7:0] $end
$upscope $end
$upscope $end
$enddefinitions $end
#0
$dumpvars
b11110010 '
b1111 &
b1 %
b0 $
b1111 #
b1 "
b11110010 !
$end
#50
b11110011 !
b11110011 '
b10 "
b10 %
#100
b11110100 !
b11110100 '
b1 $
b1110 #
b1110 &
#150
b11110101 !
b11110101 '
b11 "
b11 %
#200
b11110110 !
b11110110 '
b10 $
b1101 #
b1101 &
#250
b11110111 !
b11110111 '
b100 "
b100 %
#300
b11111000 !
b11111000 '
b11 $
b1100 #
b1100 &
#350
b11111001 !
b11111001 '
b101 "
b101 %
#400
b11111010 !
b11111010 '
b100 $
b1011 #
b1011 &
#450
b11111011 !
b11111011 '
b110 "
b110 %
#500
b11111100 !
b11111100 '
b101 $
b1010 #
b1010 &
#550
b11111101 !
b11111101 '
b111 "
b111 %
#600
b11111110 !
b11111110 '
b110 $
b1001 #
b1001 &
#650
b11111111 !
b11111111 '
b1000 "
b1000 %
#700
b0 !
b0 '
b111 $
b1000 #
b1000 &
#750
b1 !
b1 '
b1001 "
b1001 %
#800
b10 !
b10 '
b1000 $
b111 #
b111 &
#850
b11 !
b11 '
b1010 "
b1010 %
#900
b100 !
b100 '
b1001 $
b110 #
b110 &
#950
b101 !
b101 '
b1011 "
b1011 %
#1000
b110 !
b110 '
b1010 $
b101 #
b101 &
